<?xml version="1.0" encoding="UTF-8" standalone="no"?>
<Note>
    <Nota idNota="2207100">
        <nr>100</nr>
        <valoare>10.0</valoare>
        <predat>9</predat>
        <deadline>10</deadline>
        <feedback>feedback good</feedback>
    </Nota>
</Note>
<?xml version="1.0" encoding="UTF-8" standalone="no"?>
<Note>
    <Nota idNota="2207100">
        <nr>100</nr>
        <valoare>10.0</valoare>
        <predat>9</predat>
        <deadline>10</deadline>
        <feedback>feedback good</feedback>
    </Nota>
</Note>
<?xml version="1.0" encoding="UTF-8" standalone="no"?>
<Note>
    <Nota idNota="2207100">
        <nr>100</nr>
        <valoare>10.0</valoare>
        <predat>9</predat>
        <deadline>10</deadline>
        <feedback>feedback good</feedback>
    </Nota>
</Note>
<?xml version="1.0" encoding="UTF-8" standalone="no"?>
<Note>
    <Nota idNota="2207100">
        <nr>100</nr>
        <valoare>10.0</valoare>
        <predat>9</predat>
        <deadline>10</deadline>
        <feedback>feedback good</feedback>
    </Nota>
</Note>
<?xml version="1.0" encoding="UTF-8" standalone="no"?>
<Note>
    <Nota idNota="2207100">
        <nr>100</nr>
        <valoare>10.0</valoare>
        <predat>9</predat>
        <deadline>10</deadline>
        <feedback>feedback good</feedback>
    </Nota>
</Note>
